<?xml version="1.0" encoding="UTF-8"?>
<fb version="0.9.6" size="34382">
  <f>
    <added t="I">8</added>
    <cycles t="I">1</cycles>
    <deleted t="I">8</deleted>
    <error t="S">Judge github-events stopped by timeout after 3m0s: execution expired</error>
    <inserted t="I">8</inserted>
    <seconds t="F">367.541477529</seconds>
    <version t="S">0.39.2</version>
    <what t="S">judges-summary</what>
    <when t="T">2025-06-11T04:36:17Z</when>
  </f>
  <f>
    <_id t="I">1</_id>
    <_time t="T">2025-06-11T04:31:36Z</_time>
    <_version t="S">0.9.10/0.39.2/</_version>
    <total_active_contributors t="I">13</total_active_contributors>
    <what t="S">dimensions-of-terrain</what>
    <when t="T">2025-06-11T04:30:10Z</when>
  </f>
  <f>
    <_id t="I">2</_id>
    <_time t="T">2025-06-11T04:31:48Z</_time>
    <_version t="S">0.9.10/0.39.2/</_version>
    <latest t="I">0</latest>
    <repository t="I">510082372</repository>
    <what t="S">min-issue-was-found</what>
    <where t="S">github</where>
  </f>
  <f>
    <_id t="I">3</_id>
    <_time t="T">2025-06-11T04:31:48Z</_time>
    <_version t="S">0.9.10/0.39.2/</_version>
    <latest t="I">0</latest>
    <repository t="I">574534248</repository>
    <what t="S">min-issue-was-found</what>
    <where t="S">github</where>
  </f>
  <f>
    <_id t="I">4</_id>
    <_time t="T">2025-06-11T04:31:48Z</_time>
    <_version t="S">0.9.10/0.39.2/</_version>
    <latest t="I">0</latest>
    <repository t="I">970961472</repository>
    <what t="S">min-issue-was-found</what>
    <where t="S">github</where>
  </f>
  <f>
    <_id t="I">5</_id>
    <_time t="T">2025-06-11T04:31:48Z</_time>
    <_version t="S">0.9.10/0.39.2/</_version>
    <latest t="I">0</latest>
    <repository t="I">840332960</repository>
    <what t="S">min-issue-was-found</what>
    <where t="S">github</where>
  </f>
  <f>
    <_id t="I">6</_id>
    <_time t="T">2025-06-11T04:31:48Z</_time>
    <_version t="S">0.9.10/0.39.2/</_version>
    <latest t="I">0</latest>
    <repository t="I">493235807</repository>
    <what t="S">min-issue-was-found</what>
    <where t="S">github</where>
  </f>
  <f>
    <_id t="I">7</_id>
    <_time t="T">2025-06-11T04:31:48Z</_time>
    <_version t="S">0.9.10/0.39.2/</_version>
    <latest t="I">0</latest>
    <repository t="I">403396472</repository>
    <what t="S">min-issue-was-found</what>
    <where t="S">github</where>
  </f>
  <f>
    <_id t="I">8</_id>
    <_time t="T">2025-06-11T04:31:48Z</_time>
    <_version t="S">0.9.10/0.39.2/</_version>
    <latest t="I">0</latest>
    <repository t="I">490258619</repository>
    <what t="S">min-issue-was-found</what>
    <where t="S">github</where>
  </f>
  <f>
    <_id t="I">9</_id>
    <_time t="T">2025-06-11T04:31:48Z</_time>
    <_version t="S">0.9.10/0.39.2/</_version>
    <latest t="I">0</latest>
    <repository t="I">447446664</repository>
    <what t="S">min-issue-was-found</what>
    <where t="S">github</where>
  </f>
  <f>
    <_id t="I">10</_id>
    <_time t="T">2025-06-11T04:31:48Z</_time>
    <_version t="S">0.9.10/0.39.2/</_version>
    <latest t="I">0</latest>
    <repository t="I">519299365</repository>
    <what t="S">min-issue-was-found</what>
    <where t="S">github</where>
  </f>
  <f>
    <_id t="I">11</_id>
    <_time t="T">2025-06-11T04:31:48Z</_time>
    <_version t="S">0.9.10/0.39.2/</_version>
    <latest t="I">0</latest>
    <repository t="I">731516758</repository>
    <what t="S">min-issue-was-found</what>
    <where t="S">github</where>
  </f>
  <f>
    <_id t="I">12</_id>
    <_time t="T">2025-06-11T04:31:48Z</_time>
    <_version t="S">0.9.10/0.39.2/</_version>
    <latest t="I">0</latest>
    <repository t="I">798766850</repository>
    <what t="S">min-issue-was-found</what>
    <where t="S">github</where>
  </f>
  <f>
    <_id t="I">13</_id>
    <_time t="T">2025-06-11T04:31:48Z</_time>
    <_version t="S">0.9.10/0.39.2/</_version>
    <latest t="I">0</latest>
    <repository t="I">489321585</repository>
    <what t="S">min-issue-was-found</what>
    <where t="S">github</where>
  </f>
  <f>
    <_id t="I">14</_id>
    <_time t="T">2025-06-11T04:31:48Z</_time>
    <_version t="S">0.9.10/0.39.2/</_version>
    <latest t="I">0</latest>
    <repository t="I">671896902</repository>
    <what t="S">min-issue-was-found</what>
    <where t="S">github</where>
  </f>
  <f>
    <_id t="I">15</_id>
    <_time t="T">2025-06-11T04:31:48Z</_time>
    <_version t="S">0.9.10/0.39.2/</_version>
    <latest t="I">0</latest>
    <repository t="I">482612876</repository>
    <what t="S">min-issue-was-found</what>
    <where t="S">github</where>
  </f>
  <f>
    <_id t="I">16</_id>
    <_time t="T">2025-06-11T04:31:48Z</_time>
    <_version t="S">0.9.10/0.39.2/</_version>
    <latest t="I">0</latest>
    <repository t="I">501259435</repository>
    <what t="S">min-issue-was-found</what>
    <where t="S">github</where>
  </f>
  <f>
    <_id t="I">17</_id>
    <_time t="T">2025-06-11T04:31:48Z</_time>
    <_version t="S">0.9.10/0.39.2/</_version>
    <latest t="I">0</latest>
    <repository t="I">731438612</repository>
    <what t="S">min-issue-was-found</what>
    <where t="S">github</where>
  </f>
  <f>
    <_id t="I">18</_id>
    <_time t="T">2025-06-11T04:31:48Z</_time>
    <_version t="S">0.9.10/0.39.2/</_version>
    <latest t="I">0</latest>
    <repository t="I">492899189</repository>
    <what t="S">min-issue-was-found</what>
    <where t="S">github</where>
  </f>
  <f>
    <_id t="I">19</_id>
    <_time t="T">2025-06-11T04:31:48Z</_time>
    <_version t="S">0.9.10/0.39.2/</_version>
    <latest t="I">0</latest>
    <repository t="I">955159947</repository>
    <what t="S">min-issue-was-found</what>
    <where t="S">github</where>
  </f>
  <f>
    <_id t="I">20</_id>
    <_time t="T">2025-06-11T04:31:48Z</_time>
    <_version t="S">0.9.10/0.39.2/</_version>
    <latest t="I">0</latest>
    <repository t="I">558766137</repository>
    <what t="S">min-issue-was-found</what>
    <where t="S">github</where>
  </f>
  <f>
    <_id t="I">21</_id>
    <_time t="T">2025-06-11T04:31:48Z</_time>
    <_version t="S">0.9.10/0.39.2/</_version>
    <latest t="I">0</latest>
    <repository t="I">483303722</repository>
    <what t="S">min-issue-was-found</what>
    <where t="S">github</where>
  </f>
  <f>
    <_id t="I">22</_id>
    <_time t="T">2025-06-11T04:31:48Z</_time>
    <_version t="S">0.9.10/0.39.2/</_version>
    <latest t="I">0</latest>
    <repository t="I">784310467</repository>
    <what t="S">min-issue-was-found</what>
    <where t="S">github</where>
  </f>
  <f>
    <_id t="I">23</_id>
    <_time t="T">2025-06-11T04:31:48Z</_time>
    <_version t="S">0.9.10/0.39.2/</_version>
    <latest t="I">0</latest>
    <repository t="I">570457023</repository>
    <what t="S">min-issue-was-found</what>
    <where t="S">github</where>
  </f>
  <f>
    <_id t="I">24</_id>
    <_time t="T">2025-06-11T04:31:48Z</_time>
    <_version t="S">0.9.10/0.39.2/</_version>
    <latest t="I">0</latest>
    <repository t="I">501942888</repository>
    <what t="S">min-issue-was-found</what>
    <where t="S">github</where>
  </f>
  <f>
    <_id t="I">25</_id>
    <_time t="T">2025-06-11T04:31:48Z</_time>
    <_version t="S">0.9.10/0.39.2/</_version>
    <latest t="I">0</latest>
    <repository t="I">977982682</repository>
    <what t="S">min-issue-was-found</what>
    <where t="S">github</where>
  </f>
  <f>
    <_id t="I">26</_id>
    <_time t="T">2025-06-11T04:31:48Z</_time>
    <_version t="S">0.9.10/0.39.2/</_version>
    <latest t="I">0</latest>
    <repository t="I">546194972</repository>
    <what t="S">min-issue-was-found</what>
    <where t="S">github</where>
  </f>
  <f>
    <_id t="I">27</_id>
    <_time t="T">2025-06-11T04:31:48Z</_time>
    <_version t="S">0.9.10/0.39.2/</_version>
    <latest t="I">0</latest>
    <repository t="I">490157985</repository>
    <what t="S">min-issue-was-found</what>
    <where t="S">github</where>
  </f>
  <f>
    <_id t="I">28</_id>
    <_time t="T">2025-06-11T04:31:48Z</_time>
    <_version t="S">0.9.10/0.39.2/</_version>
    <latest t="I">0</latest>
    <repository t="I">889819508</repository>
    <what t="S">min-issue-was-found</what>
    <where t="S">github</where>
  </f>
  <f>
    <_id t="I">29</_id>
    <_time t="T">2025-06-11T04:31:48Z</_time>
    <_version t="S">0.9.10/0.39.2/</_version>
    <latest t="I">0</latest>
    <repository t="I">551486781</repository>
    <what t="S">min-issue-was-found</what>
    <where t="S">github</where>
  </f>
  <f>
    <_id t="I">30</_id>
    <_time t="T">2025-06-11T04:31:48Z</_time>
    <_version t="S">0.9.10/0.39.2/</_version>
    <latest t="I">0</latest>
    <repository t="I">531151981</repository>
    <what t="S">min-issue-was-found</what>
    <where t="S">github</where>
  </f>
  <f>
    <_id t="I">31</_id>
    <_time t="T">2025-06-11T04:31:48Z</_time>
    <_version t="S">0.9.10/0.39.2/</_version>
    <latest t="I">0</latest>
    <repository t="I">499536612</repository>
    <what t="S">min-issue-was-found</what>
    <where t="S">github</where>
  </f>
  <f>
    <_id t="I">32</_id>
    <_time t="T">2025-06-11T04:31:48Z</_time>
    <_version t="S">0.9.10/0.39.2/</_version>
    <latest t="I">0</latest>
    <repository t="I">559427983</repository>
    <what t="S">min-issue-was-found</what>
    <where t="S">github</where>
  </f>
  <f>
    <_id t="I">33</_id>
    <_time t="T">2025-06-11T04:31:48Z</_time>
    <_version t="S">0.9.10/0.39.2/</_version>
    <latest t="I">0</latest>
    <repository t="I">565789755</repository>
    <what t="S">min-issue-was-found</what>
    <where t="S">github</where>
  </f>
  <f>
    <_id t="I">34</_id>
    <_time t="T">2025-06-11T04:31:48Z</_time>
    <_version t="S">0.9.10/0.39.2/</_version>
    <latest t="I">0</latest>
    <repository t="I">73056727</repository>
    <what t="S">min-issue-was-found</what>
    <where t="S">github</where>
  </f>
  <f>
    <_id t="I">35</_id>
    <_time t="T">2025-06-11T04:31:48Z</_time>
    <_version t="S">0.9.10/0.39.2/</_version>
    <latest t="I">0</latest>
    <repository t="I">574459304</repository>
    <what t="S">min-issue-was-found</what>
    <where t="S">github</where>
  </f>
  <f>
    <_id t="I">36</_id>
    <_time t="T">2025-06-11T04:31:48Z</_time>
    <_version t="S">0.9.10/0.39.2/</_version>
    <latest t="I">0</latest>
    <repository t="I">624420387</repository>
    <what t="S">min-issue-was-found</what>
    <where t="S">github</where>
  </f>
  <f>
    <_id t="I">37</_id>
    <_time t="T">2025-06-11T04:31:48Z</_time>
    <_version t="S">0.9.10/0.39.2/</_version>
    <latest t="I">0</latest>
    <repository t="I">510102039</repository>
    <what t="S">min-issue-was-found</what>
    <where t="S">github</where>
  </f>
  <f>
    <_id t="I">38</_id>
    <_time t="T">2025-06-11T04:31:48Z</_time>
    <_version t="S">0.9.10/0.39.2/</_version>
    <latest t="I">0</latest>
    <repository t="I">568705267</repository>
    <what t="S">min-issue-was-found</what>
    <where t="S">github</where>
  </f>
  <f>
    <_id t="I">39</_id>
    <_time t="T">2025-06-11T04:31:48Z</_time>
    <_version t="S">0.9.10/0.39.2/</_version>
    <latest t="I">0</latest>
    <repository t="I">519246071</repository>
    <what t="S">min-issue-was-found</what>
    <where t="S">github</where>
  </f>
  <f>
    <_id t="I">40</_id>
    <_time t="T">2025-06-11T04:31:48Z</_time>
    <_version t="S">0.9.10/0.39.2/</_version>
    <latest t="I">0</latest>
    <repository t="I">396732517</repository>
    <what t="S">min-issue-was-found</what>
    <where t="S">github</where>
  </f>
  <f>
    <_id t="I">41</_id>
    <_time t="T">2025-06-11T04:31:48Z</_time>
    <_version t="S">0.9.10/0.39.2/</_version>
    <latest t="I">0</latest>
    <repository t="I">13623548</repository>
    <what t="S">min-issue-was-found</what>
    <where t="S">github</where>
  </f>
  <f>
    <_id t="I">42</_id>
    <_time t="T">2025-06-11T04:31:48Z</_time>
    <_version t="S">0.9.10/0.39.2/</_version>
    <latest t="I">0</latest>
    <repository t="I">733919301</repository>
    <what t="S">min-issue-was-found</what>
    <where t="S">github</where>
  </f>
  <f>
    <_id t="I">43</_id>
    <_time t="T">2025-06-11T04:31:49Z</_time>
    <_version t="S">0.9.10/0.39.2/</_version>
    <latest t="I">0</latest>
    <repository t="I">490221501</repository>
    <what t="S">min-issue-was-found</what>
    <where t="S">github</where>
  </f>
  <f>
    <_id t="I">44</_id>
    <_time t="T">2025-06-11T04:31:49Z</_time>
    <_version t="S">0.9.10/0.39.2/</_version>
    <latest t="I">0</latest>
    <repository t="I">386420319</repository>
    <what t="S">min-issue-was-found</what>
    <where t="S">github</where>
  </f>
  <f>
    <_id t="I">45</_id>
    <_time t="T">2025-06-11T04:31:49Z</_time>
    <_version t="S">0.9.10/0.39.2/</_version>
    <latest t="I">0</latest>
    <repository t="I">543969974</repository>
    <what t="S">min-issue-was-found</what>
    <where t="S">github</where>
  </f>
  <f>
    <_id t="I">46</_id>
    <_time t="T">2025-06-11T04:31:49Z</_time>
    <_version t="S">0.9.10/0.39.2/</_version>
    <latest t="I">0</latest>
    <repository t="I">721146770</repository>
    <what t="S">min-issue-was-found</what>
    <where t="S">github</where>
  </f>
  <f>
    <_id t="I">47</_id>
    <_time t="T">2025-06-11T04:31:49Z</_time>
    <_version t="S">0.9.10/0.39.2/</_version>
    <latest t="I">50628571777</latest>
    <repository t="I">510102039</repository>
    <what t="S">events-were-scanned</what>
    <where t="S">github</where>
  </f>
  <f>
    <_id t="I">48</_id>
    <_time t="T">2025-06-11T04:31:51Z</_time>
    <_version t="S">0.9.10/0.39.2/</_version>
    <details t="S">The issue objectionary/lints#630 has been closed by @h1alexbel.</details>
    <event_id t="I">50678008419</event_id>
    <event_type t="S">IssuesEvent</event_type>
    <is_human t="I">1</is_human>
    <issue t="I">630</issue>
    <repository t="I">889819508</repository>
    <what t="S">issue-was-closed</what>
    <when t="T">2025-06-09T13:58:40Z</when>
    <where t="S">github</where>
    <who t="I">83453843</who>
  </f>
  <f>
    <_id t="I">49</_id>
    <_time t="T">2025-06-11T04:31:52Z</_time>
    <_version t="S">0.9.10/0.39.2/</_version>
    <commit t="S">5bac39ae86f5fecfa930480dc118d36851d894f9</commit>
    <default_branch t="S">master</default_branch>
    <details t="S">A new Git push #24777471077 has arrived to objectionary/lints, made by @yegor256 (default branch is 'master'), not associated with any pull request.</details>
    <event_id t="I">50660420676</event_id>
    <event_type t="S">PushEvent</event_type>
    <is_human t="I">1</is_human>
    <push_id t="I">24777471077</push_id>
    <ref t="S">refs/heads/master</ref>
    <repository t="I">889819508</repository>
    <to_master t="I">1</to_master>
    <what t="S">git-was-pushed</what>
    <when t="T">2025-06-09T05:47:49Z</when>
    <where t="S">github</where>
    <who t="I">526301</who>
  </f>
  <f>
    <_id t="I">50</_id>
    <_time t="T">2025-06-11T04:31:52Z</_time>
    <_version t="S">0.9.10/0.39.2/</_version>
    <details t="S">The issue objectionary/lints#634 has been closed by @yegor256.</details>
    <event_id t="I">50660057848</event_id>
    <event_type t="S">IssuesEvent</event_type>
    <is_human t="I">1</is_human>
    <issue t="I">634</issue>
    <repository t="I">889819508</repository>
    <what t="S">issue-was-closed</what>
    <when t="T">2025-06-09T05:32:31Z</when>
    <where t="S">github</where>
    <who t="I">526301</who>
  </f>
  <f>
    <_id t="I">51</_id>
    <_time t="T">2025-06-11T04:31:52Z</_time>
    <_version t="S">0.9.10/0.39.2/</_version>
    <details t="S">The issue objectionary/lints#637 has been opened by @yegor256.</details>
    <event_id t="I">50649383905</event_id>
    <event_type t="S">IssuesEvent</event_type>
    <is_human t="I">1</is_human>
    <issue t="I">637</issue>
    <repository t="I">889819508</repository>
    <what t="S">issue-was-opened</what>
    <when t="T">2025-06-08T17:13:42Z</when>
    <where t="S">github</where>
    <who t="I">526301</who>
  </f>
  <f>
    <_id t="I">52</_id>
    <_time t="T">2025-06-11T04:31:52Z</_time>
    <_version t="S">0.9.10/0.39.2/</_version>
    <details t="S">The issue objectionary/lints#636 has been opened by @yegor256.</details>
    <event_id t="I">50649274129</event_id>
    <event_type t="S">IssuesEvent</event_type>
    <is_human t="I">1</is_human>
    <issue t="I">636</issue>
    <repository t="I">889819508</repository>
    <what t="S">issue-was-opened</what>
    <when t="T">2025-06-08T17:05:02Z</when>
    <where t="S">github</where>
    <who t="I">526301</who>
  </f>
  <f>
    <_id t="I">53</_id>
    <_time t="T">2025-06-11T04:31:52Z</_time>
    <_version t="S">0.9.10/0.39.2/</_version>
    <details t="S">The issue objectionary/lints#635 has been opened by @yegor256.</details>
    <event_id t="I">50648835471</event_id>
    <event_type t="S">IssuesEvent</event_type>
    <is_human t="I">1</is_human>
    <issue t="I">635</issue>
    <repository t="I">889819508</repository>
    <what t="S">issue-was-opened</what>
    <when t="T">2025-06-08T16:30:55Z</when>
    <where t="S">github</where>
    <who t="I">526301</who>
  </f>
  <f>
    <_id t="I">54</_id>
    <_time t="T">2025-06-11T04:31:52Z</_time>
    <_version t="S">0.9.10/0.39.2/</_version>
    <details t="S">The issue objectionary/lints#634 has been opened by @yegor256.</details>
    <event_id t="I">50648767340</event_id>
    <event_type t="S">IssuesEvent</event_type>
    <is_human t="I">1</is_human>
    <issue t="I">634</issue>
    <repository t="I">889819508</repository>
    <what t="S">issue-was-opened</what>
    <when t="T">2025-06-08T16:25:43Z</when>
    <where t="S">github</where>
    <who t="I">526301</who>
  </f>
  <f>
    <_id t="I">55</_id>
    <_time t="T">2025-06-11T04:31:52Z</_time>
    <_version t="S">0.9.10/0.39.2/</_version>
    <branch t="S">624</branch>
    <details t="S">The pull request objectionary/lints#633 has been opened by @h1alexbel.</details>
    <event_id t="I">50645983241</event_id>
    <event_type t="S">PullRequestEvent</event_type>
    <is_human t="I">1</is_human>
    <issue t="I">633</issue>
    <repository t="I">889819508</repository>
    <what t="S">pull-was-opened</what>
    <when t="T">2025-06-08T13:00:47Z</when>
    <where t="S">github</where>
    <who t="I">83453843</who>
  </f>
  <f>
    <_id t="I">56</_id>
    <_time t="T">2025-06-11T04:31:52Z</_time>
    <_version t="S">0.9.10/0.39.2/</_version>
    <branch t="S">renovate/org.pitest-pitest-maven-1.x</branch>
    <comments t="I">2</comments>
    <comments_appreciated t="I">0</comments_appreciated>
    <comments_by_author t="I">0</comments_by_author>
    <comments_by_reviewers t="I">2</comments_by_reviewers>
    <comments_resolved t="I">0</comments_resolved>
    <comments_to_code t="I">0</comments_to_code>
    <details t="S">The pull request objectionary/lints#628 has been closed by @yegor256, with 2 HoC and 2 comments.</details>
    <event_id t="I">50645908350</event_id>
    <event_type t="S">PullRequestEvent</event_type>
    <failed_builds t="I">1</failed_builds>
    <hoc t="I">2</hoc>
    <is_human t="I">1</is_human>
    <issue t="I">628</issue>
    <repository t="I">889819508</repository>
    <succeeded_builds t="I">18</succeeded_builds>
    <what t="S">pull-was-merged</what>
    <when t="T">2025-06-08T12:55:29Z</when>
    <where t="S">github</where>
    <who t="I">526301</who>
  </f>
  <f>
    <_id t="I">57</_id>
    <_time t="T">2025-06-11T04:32:08Z</_time>
    <_version t="S">0.9.10/0.39.2/</_version>
    <branch t="S">renovate/org.eolang-eo-parser-0.x</branch>
    <comments t="I">2</comments>
    <comments_appreciated t="I">0</comments_appreciated>
    <comments_by_author t="I">0</comments_by_author>
    <comments_by_reviewers t="I">2</comments_by_reviewers>
    <comments_resolved t="I">0</comments_resolved>
    <comments_to_code t="I">0</comments_to_code>
    <details t="S">The pull request objectionary/lints#629 has been closed by @yegor256, with 2 HoC and 2 comments.</details>
    <event_id t="I">50645905020</event_id>
    <event_type t="S">PullRequestEvent</event_type>
    <failed_builds t="I">0</failed_builds>
    <hoc t="I">2</hoc>
    <is_human t="I">1</is_human>
    <issue t="I">629</issue>
    <repository t="I">889819508</repository>
    <succeeded_builds t="I">19</succeeded_builds>
    <what t="S">pull-was-merged</what>
    <when t="T">2025-06-08T12:55:14Z</when>
    <where t="S">github</where>
    <who t="I">526301</who>
  </f>
  <f>
    <_id t="I">58</_id>
    <_time t="T">2025-06-11T04:32:16Z</_time>
    <_version t="S">0.9.10/0.39.2/</_version>
    <branch t="S">630</branch>
    <comments t="I">3</comments>
    <comments_appreciated t="I">0</comments_appreciated>
    <comments_by_author t="I">1</comments_by_author>
    <comments_by_reviewers t="I">4</comments_by_reviewers>
    <comments_resolved t="I">0</comments_resolved>
    <comments_to_code t="I">0</comments_to_code>
    <details t="S">The pull request objectionary/lints#631 has been closed by @yegor256, with 8 HoC and 3 comments.</details>
    <event_id t="I">50644236322</event_id>
    <event_type t="S">PullRequestEvent</event_type>
    <failed_builds t="I">0</failed_builds>
    <hoc t="I">8</hoc>
    <is_human t="I">1</is_human>
    <issue t="I">631</issue>
    <repository t="I">889819508</repository>
    <succeeded_builds t="I">20</succeeded_builds>
    <what t="S">pull-was-merged</what>
    <when t="T">2025-06-08T10:43:25Z</when>
    <where t="S">github</where>
    <who t="I">526301</who>
  </f>
  <f>
    <_id t="I">59</_id>
    <_time t="T">2025-06-11T04:32:25Z</_time>
    <_version t="S">0.9.10/0.39.2/</_version>
    <comments t="I">5</comments>
    <commits t="I">2</commits>
    <details t="S">The pull request objectionary/lints#631 has been reviewed by @yegor256 with 8 HoC and 5 comments.</details>
    <event_id t="I">50644235063</event_id>
    <event_type t="S">PullRequestReviewEvent</event_type>
    <files t="I">2</files>
    <hoc t="I">8</hoc>
    <is_human t="I">1</is_human>
    <issue t="I">631</issue>
    <repository t="I">889819508</repository>
    <review_comments t="I">0</review_comments>
    <what t="S">pull-was-reviewed</what>
    <when t="T">2025-06-08T10:43:18Z</when>
    <where t="S">github</where>
    <who t="I">526301</who>
  </f>
  <f>
    <_id t="I">60</_id>
    <_time t="T">2025-06-11T04:32:26Z</_time>
    <_version t="S">0.9.10/0.39.2/</_version>
    <details t="S">The issue objectionary/lints#632 has been opened by @h1alexbel.</details>
    <event_id t="I">50643613306</event_id>
    <event_type t="S">IssuesEvent</event_type>
    <is_human t="I">1</is_human>
    <issue t="I">632</issue>
    <repository t="I">889819508</repository>
    <what t="S">issue-was-opened</what>
    <when t="T">2025-06-08T09:51:59Z</when>
    <where t="S">github</where>
    <who t="I">83453843</who>
  </f>
  <f>
    <_id t="I">61</_id>
    <_time t="T">2025-06-11T04:32:26Z</_time>
    <_version t="S">0.9.10/0.39.2/</_version>
    <branch t="S">630</branch>
    <details t="S">The pull request objectionary/lints#631 has been opened by @h1alexbel.</details>
    <event_id t="I">50643485317</event_id>
    <event_type t="S">PullRequestEvent</event_type>
    <is_human t="I">1</is_human>
    <issue t="I">631</issue>
    <repository t="I">889819508</repository>
    <what t="S">pull-was-opened</what>
    <when t="T">2025-06-08T09:41:33Z</when>
    <where t="S">github</where>
    <who t="I">83453843</who>
  </f>
  <f>
    <_id t="I">62</_id>
    <_time t="T">2025-06-11T04:32:26Z</_time>
    <_version t="S">0.9.10/0.39.2/</_version>
    <details t="S">The issue objectionary/lints#607 has been closed by @h1alexbel.</details>
    <event_id t="I">50642908752</event_id>
    <event_type t="S">IssuesEvent</event_type>
    <is_human t="I">1</is_human>
    <issue t="I">607</issue>
    <repository t="I">889819508</repository>
    <what t="S">issue-was-closed</what>
    <when t="T">2025-06-08T08:51:59Z</when>
    <where t="S">github</where>
    <who t="I">83453843</who>
  </f>
  <f>
    <_id t="I">63</_id>
    <_time t="T">2025-06-11T04:32:26Z</_time>
    <_version t="S">0.9.10/0.39.2/</_version>
    <details t="S">The issue objectionary/lints#609 has been closed by @h1alexbel.</details>
    <event_id t="I">50642893853</event_id>
    <event_type t="S">IssuesEvent</event_type>
    <is_human t="I">1</is_human>
    <issue t="I">609</issue>
    <repository t="I">889819508</repository>
    <what t="S">issue-was-closed</what>
    <when t="T">2025-06-08T08:50:34Z</when>
    <where t="S">github</where>
    <who t="I">83453843</who>
  </f>
  <f>
    <_id t="I">64</_id>
    <_time t="T">2025-06-11T04:32:26Z</_time>
    <_version t="S">0.9.10/0.39.2/</_version>
    <details t="S">The issue objectionary/lints#583 has been closed by @Marat-Tim.</details>
    <event_id t="I">50628978265</event_id>
    <event_type t="S">IssuesEvent</event_type>
    <is_human t="I">1</is_human>
    <issue t="I">583</issue>
    <repository t="I">889819508</repository>
    <what t="S">issue-was-closed</what>
    <when t="T">2025-06-07T11:36:15Z</when>
    <where t="S">github</where>
    <who t="I">108345628</who>
  </f>
  <f>
    <_id t="I">65</_id>
    <_time t="T">2025-06-11T04:32:26Z</_time>
    <_version t="S">0.9.10/0.39.2/</_version>
    <details t="S">The issue objectionary/lints#630 has been opened by @github-actions[bot].</details>
    <event_id t="I">50594882203</event_id>
    <event_type t="S">IssuesEvent</event_type>
    <is_human t="I">0</is_human>
    <issue t="I">630</issue>
    <repository t="I">889819508</repository>
    <what t="S">issue-was-opened</what>
    <when t="T">2025-06-06T10:04:22Z</when>
    <where t="S">github</where>
    <who t="I">41898282</who>
  </f>
  <f>
    <_id t="I">66</_id>
    <_time t="T">2025-06-11T04:32:26Z</_time>
    <_version t="S">0.9.10/0.39.2/</_version>
    <branch t="S">version-up</branch>
    <comments t="I">1</comments>
    <comments_appreciated t="I">0</comments_appreciated>
    <comments_by_author t="I">0</comments_by_author>
    <comments_by_reviewers t="I">1</comments_by_reviewers>
    <comments_resolved t="I">0</comments_resolved>
    <comments_to_code t="I">0</comments_to_code>
    <details t="S">The pull request objectionary/lints#620 has been closed by @yegor256, with 2 HoC and 1 comments.</details>
    <event_id t="I">50591881007</event_id>
    <event_type t="S">PullRequestEvent</event_type>
    <failed_builds t="I">0</failed_builds>
    <hoc t="I">2</hoc>
    <is_human t="I">1</is_human>
    <issue t="I">620</issue>
    <repository t="I">889819508</repository>
    <succeeded_builds t="I">0</succeeded_builds>
    <what t="S">pull-was-merged</what>
    <when t="T">2025-06-06T08:44:44Z</when>
    <where t="S">github</where>
    <who t="I">526301</who>
  </f>
  <f>
    <_id t="I">67</_id>
    <_time t="T">2025-06-11T04:32:27Z</_time>
    <_version t="S">0.9.10/0.39.2/</_version>
    <branch t="S">renovate/yegor256-copyrights-action-0.x</branch>
    <comments t="I">4</comments>
    <comments_appreciated t="I">1</comments_appreciated>
    <comments_by_author t="I">0</comments_by_author>
    <comments_by_reviewers t="I">4</comments_by_reviewers>
    <comments_resolved t="I">0</comments_resolved>
    <comments_to_code t="I">0</comments_to_code>
    <details t="S">The pull request objectionary/lints#619 has been closed by @yegor256, with 2 HoC and 4 comments.</details>
    <event_id t="I">50591875672</event_id>
    <event_type t="S">PullRequestEvent</event_type>
    <failed_builds t="I">1</failed_builds>
    <hoc t="I">2</hoc>
    <is_human t="I">1</is_human>
    <issue t="I">619</issue>
    <repository t="I">889819508</repository>
    <succeeded_builds t="I">19</succeeded_builds>
    <what t="S">pull-was-merged</what>
    <when t="T">2025-06-06T08:44:35Z</when>
    <where t="S">github</where>
    <who t="I">526301</who>
  </f>
  <f>
    <_id t="I">68</_id>
    <_time t="T">2025-06-11T04:32:36Z</_time>
    <_version t="S">0.9.10/0.39.2/</_version>
    <branch t="S">renovate/org.pitest-pitest-junit5-plugin-1.x</branch>
    <comments t="I">4</comments>
    <comments_appreciated t="I">1</comments_appreciated>
    <comments_by_author t="I">0</comments_by_author>
    <comments_by_reviewers t="I">4</comments_by_reviewers>
    <comments_resolved t="I">0</comments_resolved>
    <comments_to_code t="I">0</comments_to_code>
    <details t="S">The pull request objectionary/lints#611 has been closed by @yegor256, with 2 HoC and 4 comments.</details>
    <event_id t="I">50591863144</event_id>
    <event_type t="S">PullRequestEvent</event_type>
    <failed_builds t="I">0</failed_builds>
    <hoc t="I">2</hoc>
    <is_human t="I">1</is_human>
    <issue t="I">611</issue>
    <repository t="I">889819508</repository>
    <succeeded_builds t="I">20</succeeded_builds>
    <what t="S">pull-was-merged</what>
    <when t="T">2025-06-06T08:44:16Z</when>
    <where t="S">github</where>
    <who t="I">526301</who>
  </f>
  <f>
    <_id t="I">69</_id>
    <_time t="T">2025-06-11T04:32:46Z</_time>
    <_version t="S">0.9.10/0.39.2/</_version>
    <branch t="S">renovate/groovy-monorepo</branch>
    <comments t="I">4</comments>
    <comments_appreciated t="I">1</comments_appreciated>
    <comments_by_author t="I">0</comments_by_author>
    <comments_by_reviewers t="I">4</comments_by_reviewers>
    <comments_resolved t="I">0</comments_resolved>
    <comments_to_code t="I">0</comments_to_code>
    <details t="S">The pull request objectionary/lints#621 has been closed by @yegor256, with 2 HoC and 4 comments.</details>
    <event_id t="I">50591856965</event_id>
    <event_type t="S">PullRequestEvent</event_type>
    <failed_builds t="I">0</failed_builds>
    <hoc t="I">2</hoc>
    <is_human t="I">1</is_human>
    <issue t="I">621</issue>
    <repository t="I">889819508</repository>
    <succeeded_builds t="I">20</succeeded_builds>
    <what t="S">pull-was-merged</what>
    <when t="T">2025-06-06T08:44:06Z</when>
    <where t="S">github</where>
    <who t="I">526301</who>
  </f>
  <f>
    <_id t="I">70</_id>
    <_time t="T">2025-06-11T04:32:55Z</_time>
    <_version t="S">0.9.10/0.39.2/</_version>
    <branch t="S">renovate/org.eolang-eo-parser-0.x</branch>
    <details t="S">The pull request objectionary/lints#629 has been opened by @renovate[bot].</details>
    <event_id t="I">50591851847</event_id>
    <event_type t="S">PullRequestEvent</event_type>
    <is_human t="I">0</is_human>
    <issue t="I">629</issue>
    <repository t="I">889819508</repository>
    <what t="S">pull-was-opened</what>
    <when t="T">2025-06-06T08:43:58Z</when>
    <where t="S">github</where>
    <who t="I">29139614</who>
  </f>
  <f>
    <_id t="I">71</_id>
    <_time t="T">2025-06-11T04:32:55Z</_time>
    <_version t="S">0.9.10/0.39.2/</_version>
    <branch t="S">renovate/com.opencsv-opencsv-5.x</branch>
    <comments t="I">2</comments>
    <comments_appreciated t="I">0</comments_appreciated>
    <comments_by_author t="I">0</comments_by_author>
    <comments_by_reviewers t="I">2</comments_by_reviewers>
    <comments_resolved t="I">0</comments_resolved>
    <comments_to_code t="I">0</comments_to_code>
    <details t="S">The pull request objectionary/lints#623 has been closed by @yegor256, with 2 HoC and 2 comments.</details>
    <event_id t="I">50591850394</event_id>
    <event_type t="S">PullRequestEvent</event_type>
    <failed_builds t="I">1</failed_builds>
    <hoc t="I">2</hoc>
    <is_human t="I">1</is_human>
    <issue t="I">623</issue>
    <repository t="I">889819508</repository>
    <succeeded_builds t="I">19</succeeded_builds>
    <what t="S">pull-was-merged</what>
    <when t="T">2025-06-06T08:43:56Z</when>
    <where t="S">github</where>
    <who t="I">526301</who>
  </f>
  <f>
    <_id t="I">72</_id>
    <_time t="T">2025-06-11T04:33:03Z</_time>
    <_version t="S">0.9.10/0.39.2/</_version>
    <branch t="S">renovate/org.pitest-pitest-maven-1.x</branch>
    <details t="S">The pull request objectionary/lints#628 has been opened by @renovate[bot].</details>
    <event_id t="I">50591847039</event_id>
    <event_type t="S">PullRequestEvent</event_type>
    <is_human t="I">0</is_human>
    <issue t="I">628</issue>
    <repository t="I">889819508</repository>
    <what t="S">pull-was-opened</what>
    <when t="T">2025-06-06T08:43:50Z</when>
    <where t="S">github</where>
    <who t="I">29139614</who>
  </f>
  <f>
    <_id t="I">73</_id>
    <_time t="T">2025-06-11T04:33:04Z</_time>
    <_version t="S">0.9.10/0.39.2/</_version>
    <branch t="S">renovate/crate-ci-typos-1.x</branch>
    <comments t="I">2</comments>
    <comments_appreciated t="I">0</comments_appreciated>
    <comments_by_author t="I">0</comments_by_author>
    <comments_by_reviewers t="I">2</comments_by_reviewers>
    <comments_resolved t="I">0</comments_resolved>
    <comments_to_code t="I">0</comments_to_code>
    <details t="S">The pull request objectionary/lints#625 has been closed by @yegor256, with 2 HoC and 2 comments.</details>
    <event_id t="I">50591838162</event_id>
    <event_type t="S">PullRequestEvent</event_type>
    <failed_builds t="I">1</failed_builds>
    <hoc t="I">2</hoc>
    <is_human t="I">1</is_human>
    <issue t="I">625</issue>
    <repository t="I">889819508</repository>
    <succeeded_builds t="I">19</succeeded_builds>
    <what t="S">pull-was-merged</what>
    <when t="T">2025-06-06T08:43:35Z</when>
    <where t="S">github</where>
    <who t="I">526301</who>
  </f>
  <f>
    <_id t="I">74</_id>
    <_time t="T">2025-06-11T04:33:12Z</_time>
    <_version t="S">0.9.10/0.39.2/</_version>
    <branch t="S">renovate/com.jcabi-parent-0.x</branch>
    <comments t="I">2</comments>
    <comments_appreciated t="I">0</comments_appreciated>
    <comments_by_author t="I">0</comments_by_author>
    <comments_by_reviewers t="I">2</comments_by_reviewers>
    <comments_resolved t="I">0</comments_resolved>
    <comments_to_code t="I">0</comments_to_code>
    <details t="S">The pull request objectionary/lints#626 has been closed by @yegor256, with 2 HoC and 2 comments.</details>
    <event_id t="I">50591831856</event_id>
    <event_type t="S">PullRequestEvent</event_type>
    <failed_builds t="I">1</failed_builds>
    <hoc t="I">2</hoc>
    <is_human t="I">1</is_human>
    <issue t="I">626</issue>
    <repository t="I">889819508</repository>
    <succeeded_builds t="I">19</succeeded_builds>
    <what t="S">pull-was-merged</what>
    <when t="T">2025-06-06T08:43:26Z</when>
    <where t="S">github</where>
    <who t="I">526301</who>
  </f>
  <f>
    <_id t="I">75</_id>
    <_time t="T">2025-06-11T04:33:21Z</_time>
    <_version t="S">0.9.10/0.39.2/</_version>
    <details t="S">The issue objectionary/lints#627 has been opened by @0pdd.</details>
    <event_id t="I">50591823278</event_id>
    <event_type t="S">IssuesEvent</event_type>
    <is_human t="I">0</is_human>
    <issue t="I">627</issue>
    <repository t="I">889819508</repository>
    <what t="S">issue-was-opened</what>
    <when t="T">2025-06-06T08:43:12Z</when>
    <where t="S">github</where>
    <who t="I">24456188</who>
  </f>
  <f>
    <_id t="I">76</_id>
    <_time t="T">2025-06-11T04:33:21Z</_time>
    <_version t="S">0.9.10/0.39.2/</_version>
    <details t="S">The issue objectionary/lints#405 has been closed by @0pdd.</details>
    <event_id t="I">50591821591</event_id>
    <event_type t="S">IssuesEvent</event_type>
    <is_human t="I">0</is_human>
    <issue t="I">405</issue>
    <repository t="I">889819508</repository>
    <what t="S">issue-was-closed</what>
    <when t="T">2025-06-06T08:43:09Z</when>
    <where t="S">github</where>
    <who t="I">24456188</who>
  </f>
  <f>
    <_id t="I">77</_id>
    <_time t="T">2025-06-11T04:33:21Z</_time>
    <_version t="S">0.9.10/0.39.2/</_version>
    <details t="S">The issue objectionary/lints#372 has been closed by @0pdd.</details>
    <event_id t="I">50591820518</event_id>
    <event_type t="S">IssuesEvent</event_type>
    <is_human t="I">0</is_human>
    <issue t="I">372</issue>
    <repository t="I">889819508</repository>
    <what t="S">issue-was-closed</what>
    <when t="T">2025-06-06T08:43:07Z</when>
    <where t="S">github</where>
    <who t="I">24456188</who>
  </f>
  <f>
    <_id t="I">78</_id>
    <_time t="T">2025-06-11T04:33:21Z</_time>
    <_version t="S">0.9.10/0.39.2/</_version>
    <branch t="S">cached-lint</branch>
    <comments t="I">49</comments>
    <comments_appreciated t="I">5</comments_appreciated>
    <comments_by_author t="I">22</comments_by_author>
    <comments_by_reviewers t="I">29</comments_by_reviewers>
    <comments_resolved t="I">0</comments_resolved>
    <comments_to_code t="I">32</comments_to_code>
    <details t="S">The pull request objectionary/lints#393 has been closed by @yegor256, with 256 HoC and 49 comments.</details>
    <event_id t="I">50591816600</event_id>
    <event_type t="S">PullRequestEvent</event_type>
    <failed_builds t="I">1</failed_builds>
    <hoc t="I">256</hoc>
    <is_human t="I">1</is_human>
    <issue t="I">393</issue>
    <repository t="I">889819508</repository>
    <succeeded_builds t="I">18</succeeded_builds>
    <what t="S">pull-was-merged</what>
    <when t="T">2025-06-06T08:43:01Z</when>
    <where t="S">github</where>
    <who t="I">526301</who>
  </f>
  <f>
    <_id t="I">79</_id>
    <_time t="T">2025-06-11T04:33:37Z</_time>
    <_version t="S">0.9.10/0.39.2/</_version>
    <comments t="I">51</comments>
    <commits t="I">19</commits>
    <details t="S">The pull request objectionary/lints#393 has been reviewed by @yegor256 with 256 HoC and 51 comments.</details>
    <event_id t="I">50590375396</event_id>
    <event_type t="S">PullRequestReviewEvent</event_type>
    <files t="I">6</files>
    <hoc t="I">256</hoc>
    <is_human t="I">1</is_human>
    <issue t="I">393</issue>
    <repository t="I">889819508</repository>
    <review_comments t="I">32</review_comments>
    <what t="S">pull-was-reviewed</what>
    <when t="T">2025-06-06T08:03:17Z</when>
    <where t="S">github</where>
    <who t="I">526301</who>
  </f>
  <f>
    <_id t="I">80</_id>
    <_time t="T">2025-06-11T04:33:38Z</_time>
    <_version t="S">0.9.10/0.39.2/</_version>
    <comments t="I">51</comments>
    <commits t="I">19</commits>
    <details t="S">The pull request objectionary/lints#393 has been reviewed by @h1alexbel with 256 HoC and 51 comments.</details>
    <event_id t="I">50590305546</event_id>
    <event_type t="S">PullRequestReviewEvent</event_type>
    <files t="I">6</files>
    <hoc t="I">256</hoc>
    <is_human t="I">1</is_human>
    <issue t="I">393</issue>
    <repository t="I">889819508</repository>
    <review_comments t="I">32</review_comments>
    <what t="S">pull-was-reviewed</what>
    <when t="T">2025-06-06T08:01:19Z</when>
    <where t="S">github</where>
    <who t="I">83453843</who>
  </f>
  <f>
    <_id t="I">81</_id>
    <_time t="T">2025-06-11T04:33:38Z</_time>
    <_version t="S">0.9.10/0.39.2/</_version>
    <branch t="S">renovate/com.jcabi-parent-0.x</branch>
    <details t="S">The pull request objectionary/lints#626 has been opened by @renovate[bot].</details>
    <event_id t="I">50472750933</event_id>
    <event_type t="S">PullRequestEvent</event_type>
    <is_human t="I">0</is_human>
    <issue t="I">626</issue>
    <repository t="I">889819508</repository>
    <what t="S">pull-was-opened</what>
    <when t="T">2025-06-03T19:03:19Z</when>
    <where t="S">github</where>
    <who t="I">29139614</who>
  </f>
  <f>
    <_id t="I">82</_id>
    <_time t="T">2025-06-11T04:33:38Z</_time>
    <_version t="S">0.9.10/0.39.2/</_version>
    <branch t="S">renovate/crate-ci-typos-1.x</branch>
    <details t="S">The pull request objectionary/lints#625 has been opened by @renovate[bot].</details>
    <event_id t="I">50421162977</event_id>
    <event_type t="S">PullRequestEvent</event_type>
    <is_human t="I">0</is_human>
    <issue t="I">625</issue>
    <repository t="I">889819508</repository>
    <what t="S">pull-was-opened</what>
    <when t="T">2025-06-02T18:12:14Z</when>
    <where t="S">github</where>
    <who t="I">29139614</who>
  </f>
  <f>
    <_id t="I">83</_id>
    <_time t="T">2025-06-11T04:33:38Z</_time>
    <_version t="S">0.9.10/0.39.2/</_version>
    <details t="S">The issue objectionary/lints#624 has been opened by @h1alexbel.</details>
    <event_id t="I">50404236105</event_id>
    <event_type t="S">IssuesEvent</event_type>
    <is_human t="I">1</is_human>
    <issue t="I">624</issue>
    <repository t="I">889819508</repository>
    <what t="S">issue-was-opened</what>
    <when t="T">2025-06-02T11:47:22Z</when>
    <where t="S">github</where>
    <who t="I">83453843</who>
  </f>
  <f>
    <_id t="I">84</_id>
    <_time t="T">2025-06-11T04:33:38Z</_time>
    <_version t="S">0.9.10/0.39.2/</_version>
    <details t="S">The issue objectionary/lints#610 has been closed by @h1alexbel.</details>
    <event_id t="I">50399941463</event_id>
    <event_type t="S">IssuesEvent</event_type>
    <is_human t="I">1</is_human>
    <issue t="I">610</issue>
    <repository t="I">889819508</repository>
    <what t="S">issue-was-closed</what>
    <when t="T">2025-06-02T10:01:06Z</when>
    <where t="S">github</where>
    <who t="I">83453843</who>
  </f>
  <f>
    <_id t="I">85</_id>
    <_time t="T">2025-06-11T04:33:38Z</_time>
    <_version t="S">0.9.10/0.39.2/</_version>
    <branch t="S">renovate/com.opencsv-opencsv-5.x</branch>
    <details t="S">The pull request objectionary/lints#623 has been opened by @renovate[bot].</details>
    <event_id t="I">50383935913</event_id>
    <event_type t="S">PullRequestEvent</event_type>
    <is_human t="I">0</is_human>
    <issue t="I">623</issue>
    <repository t="I">889819508</repository>
    <what t="S">pull-was-opened</what>
    <when t="T">2025-06-02T00:49:56Z</when>
    <where t="S">github</where>
    <who t="I">29139614</who>
  </f>
  <f>
    <_id t="I">86</_id>
    <_time t="T">2025-06-11T04:33:38Z</_time>
    <_version t="S">0.9.10/0.39.2/</_version>
    <branch t="S">renovate/groovy-monorepo</branch>
    <details t="S">The pull request objectionary/lints#621 has been opened by @renovate[bot].</details>
    <event_id t="I">50178836942</event_id>
    <event_type t="S">PullRequestEvent</event_type>
    <is_human t="I">0</is_human>
    <issue t="I">621</issue>
    <repository t="I">889819508</repository>
    <what t="S">pull-was-opened</what>
    <when t="T">2025-05-27T09:01:48Z</when>
    <where t="S">github</where>
    <who t="I">29139614</who>
  </f>
  <f>
    <_id t="I">87</_id>
    <_time t="T">2025-06-11T04:33:38Z</_time>
    <_version t="S">0.9.10/0.39.2/</_version>
    <details t="S">The issue objectionary/lints#585 has been closed by @Marat-Tim.</details>
    <event_id t="I">50160304001</event_id>
    <event_type t="S">IssuesEvent</event_type>
    <is_human t="I">1</is_human>
    <issue t="I">585</issue>
    <repository t="I">889819508</repository>
    <what t="S">issue-was-closed</what>
    <when t="T">2025-05-26T19:58:34Z</when>
    <where t="S">github</where>
    <who t="I">108345628</who>
  </f>
  <f>
    <_id t="I">88</_id>
    <_time t="T">2025-06-11T04:33:39Z</_time>
    <_version t="S">0.9.10/0.39.2/</_version>
    <commits t="I">1884</commits>
    <contributors>
      <v t="I">83453843</v>
      <v t="I">526301</v>
      <v t="I">29139614</v>
      <v t="I">8086956</v>
      <v t="I">51804353</v>
      <v t="I">108345628</v>
      <v t="I">41898282</v>
      <v t="I">37025995</v>
    </contributors>
    <details t="S">A new release '`redundant-object` incorrectly warns about valid top EO object' has been published in objectionary/lints by @rultor.</details>
    <event_id t="I">50147921262</event_id>
    <event_type t="S">ReleaseEvent</event_type>
    <hoc t="I">16278</hoc>
    <is_human t="I">0</is_human>
    <last_commit t="S">b3e1a08535bc72080ed1e44237eb2433061bb2ba</last_commit>
    <release t="I">221005595</release>
    <repository t="I">889819508</repository>
    <tag t="S">0.0.50</tag>
    <what t="S">release-published</what>
    <when t="T">2025-05-26T13:16:11Z</when>
    <where t="S">github</where>
    <who t="I">8086956</who>
  </f>
  <f>
    <_id t="I">89</_id>
    <_time t="T">2025-06-11T04:34:02Z</_time>
    <_version t="S">0.9.10/0.39.2/</_version>
    <branch t="S">version-up</branch>
    <details t="S">The pull request objectionary/lints#620 has been opened by @github-actions[bot].</details>
    <event_id t="I">50147895924</event_id>
    <event_type t="S">PullRequestEvent</event_type>
    <is_human t="I">0</is_human>
    <issue t="I">620</issue>
    <repository t="I">889819508</repository>
    <what t="S">pull-was-opened</what>
    <when t="T">2025-05-26T13:15:39Z</when>
    <where t="S">github</where>
    <who t="I">41898282</who>
  </f>
  <f>
    <_id t="I">90</_id>
    <_time t="T">2025-06-11T04:34:02Z</_time>
    <_version t="S">0.9.10/0.39.2/</_version>
    <details t="S">A new tag '0.0.50' has been created in objectionary/lints by @rultor.</details>
    <event_id t="I">50147872090</event_id>
    <event_type t="S">CreateEvent</event_type>
    <is_human t="I">0</is_human>
    <repository t="I">889819508</repository>
    <tag t="S">0.0.50</tag>
    <what t="S">tag-was-created</what>
    <when t="T">2025-05-26T13:15:18Z</when>
    <where t="S">github</where>
    <who t="I">8086956</who>
  </f>
  <f>
    <_id t="I">91</_id>
    <_time t="T">2025-06-11T04:34:02Z</_time>
    <_version t="S">0.9.10/0.39.2/</_version>
    <branch t="S">renovate/yegor256-copyrights-action-0.x</branch>
    <details t="S">The pull request objectionary/lints#619 has been opened by @renovate[bot].</details>
    <event_id t="I">50147649791</event_id>
    <event_type t="S">PullRequestEvent</event_type>
    <is_human t="I">0</is_human>
    <issue t="I">619</issue>
    <repository t="I">889819508</repository>
    <what t="S">pull-was-opened</what>
    <when t="T">2025-05-26T13:10:06Z</when>
    <where t="S">github</where>
    <who t="I">29139614</who>
  </f>
  <f>
    <_id t="I">92</_id>
    <_time t="T">2025-06-11T04:34:02Z</_time>
    <_version t="S">0.9.10/0.39.2/</_version>
    <details t="S">The issue objectionary/lints#618 has been closed by @volodya-lombrozo.</details>
    <event_id t="I">50146937747</event_id>
    <event_type t="S">IssuesEvent</event_type>
    <is_human t="I">1</is_human>
    <issue t="I">618</issue>
    <repository t="I">889819508</repository>
    <what t="S">issue-was-closed</what>
    <when t="T">2025-05-26T12:53:56Z</when>
    <where t="S">github</where>
    <who t="I">51804353</who>
  </f>
  <f>
    <_id t="I">93</_id>
    <_time t="T">2025-06-11T04:34:03Z</_time>
    <_version t="S">0.9.10/0.39.2/</_version>
    <details t="S">The issue objectionary/lints#618 has been opened by @volodya-lombrozo.</details>
    <event_id t="I">50145753143</event_id>
    <event_type t="S">IssuesEvent</event_type>
    <is_human t="I">1</is_human>
    <issue t="I">618</issue>
    <repository t="I">889819508</repository>
    <what t="S">issue-was-opened</what>
    <when t="T">2025-05-26T12:27:20Z</when>
    <where t="S">github</where>
    <who t="I">51804353</who>
  </f>
  <f>
    <_id t="I">94</_id>
    <_time t="T">2025-06-11T04:34:03Z</_time>
    <_version t="S">0.9.10/0.39.2/</_version>
    <branch t="S">609</branch>
    <comments t="I">5</comments>
    <comments_appreciated t="I">0</comments_appreciated>
    <comments_by_author t="I">4</comments_by_author>
    <comments_by_reviewers t="I">4</comments_by_reviewers>
    <comments_resolved t="I">0</comments_resolved>
    <comments_to_code t="I">0</comments_to_code>
    <details t="S">The pull request objectionary/lints#617 has been closed by @yegor256, with 13 HoC and 5 comments.</details>
    <event_id t="I">50135452593</event_id>
    <event_type t="S">PullRequestEvent</event_type>
    <failed_builds t="I">0</failed_builds>
    <hoc t="I">13</hoc>
    <is_human t="I">1</is_human>
    <issue t="I">617</issue>
    <repository t="I">889819508</repository>
    <succeeded_builds t="I">20</succeeded_builds>
    <what t="S">pull-was-merged</what>
    <when t="T">2025-05-26T07:59:45Z</when>
    <where t="S">github</where>
    <who t="I">526301</who>
  </f>
  <f>
    <_id t="I">95</_id>
    <_time t="T">2025-06-11T04:34:13Z</_time>
    <_version t="S">0.9.10/0.39.2/</_version>
    <comments t="I">8</comments>
    <commits t="I">2</commits>
    <details t="S">The pull request objectionary/lints#617 has been reviewed by @yegor256 with 13 HoC and 8 comments.</details>
    <event_id t="I">50135448807</event_id>
    <event_type t="S">PullRequestReviewEvent</event_type>
    <files t="I">2</files>
    <hoc t="I">13</hoc>
    <is_human t="I">1</is_human>
    <issue t="I">617</issue>
    <repository t="I">889819508</repository>
    <review_comments t="I">0</review_comments>
    <what t="S">pull-was-reviewed</what>
    <when t="T">2025-05-26T07:59:38Z</when>
    <where t="S">github</where>
    <who t="I">526301</who>
  </f>
  <f>
    <_id t="I">96</_id>
    <_time t="T">2025-06-11T04:34:13Z</_time>
    <_version t="S">0.9.10/0.39.2/</_version>
    <branch t="S">610</branch>
    <comments t="I">5</comments>
    <comments_appreciated t="I">0</comments_appreciated>
    <comments_by_author t="I">4</comments_by_author>
    <comments_by_reviewers t="I">1</comments_by_reviewers>
    <comments_resolved t="I">0</comments_resolved>
    <comments_to_code t="I">0</comments_to_code>
    <details t="S">The pull request objectionary/lints#616 has been closed by @yegor256, with 465 HoC and 5 comments.</details>
    <event_id t="I">50114462185</event_id>
    <event_type t="S">PullRequestEvent</event_type>
    <failed_builds t="I">0</failed_builds>
    <hoc t="I">465</hoc>
    <is_human t="I">1</is_human>
    <issue t="I">616</issue>
    <repository t="I">889819508</repository>
    <succeeded_builds t="I">20</succeeded_builds>
    <what t="S">pull-was-merged</what>
    <when t="T">2025-05-25T10:01:10Z</when>
    <where t="S">github</where>
    <who t="I">526301</who>
  </f>
  <f>
    <_id t="I">97</_id>
    <_time t="T">2025-06-11T04:34:22Z</_time>
    <_version t="S">0.9.10/0.39.2/</_version>
    <comments t="I">5</comments>
    <commits t="I">14</commits>
    <details t="S">The pull request objectionary/lints#616 has been reviewed by @yegor256 with 465 HoC and 5 comments.</details>
    <event_id t="I">50114459671</event_id>
    <event_type t="S">PullRequestReviewEvent</event_type>
    <files t="I">12</files>
    <hoc t="I">465</hoc>
    <is_human t="I">1</is_human>
    <issue t="I">616</issue>
    <repository t="I">889819508</repository>
    <review_comments t="I">0</review_comments>
    <what t="S">pull-was-reviewed</what>
    <when t="T">2025-05-25T10:01:02Z</when>
    <where t="S">github</where>
    <who t="I">526301</who>
  </f>
  <f>
    <_id t="I">98</_id>
    <_time t="T">2025-06-11T04:34:23Z</_time>
    <_version t="S">0.9.10/0.39.2/</_version>
    <comments t="I">8</comments>
    <commits t="I">2</commits>
    <details t="S">The pull request objectionary/lints#617 has been reviewed by @maxonfjvipon with 13 HoC and 8 comments.</details>
    <event_id t="I">50065649465</event_id>
    <event_type t="S">PullRequestReviewEvent</event_type>
    <files t="I">2</files>
    <hoc t="I">13</hoc>
    <is_human t="I">1</is_human>
    <issue t="I">617</issue>
    <repository t="I">889819508</repository>
    <review_comments t="I">0</review_comments>
    <what t="S">pull-was-reviewed</what>
    <when t="T">2025-05-23T10:00:24Z</when>
    <where t="S">github</where>
    <who t="I">37025995</who>
  </f>
  <f>
    <_id t="I">99</_id>
    <_time t="T">2025-06-11T04:34:23Z</_time>
    <_version t="S">0.9.10/0.39.2/</_version>
    <branch t="S">609</branch>
    <details t="S">The pull request objectionary/lints#617 has been opened by @h1alexbel.</details>
    <event_id t="I">50062190735</event_id>
    <event_type t="S">PullRequestEvent</event_type>
    <is_human t="I">1</is_human>
    <issue t="I">617</issue>
    <repository t="I">889819508</repository>
    <what t="S">pull-was-opened</what>
    <when t="T">2025-05-23T08:35:19Z</when>
    <where t="S">github</where>
    <who t="I">83453843</who>
  </f>
  <f>
    <_id t="I">100</_id>
    <_time t="T">2025-06-11T04:34:23Z</_time>
    <_version t="S">0.9.10/0.39.2/</_version>
    <comments t="I">5</comments>
    <commits t="I">14</commits>
    <details t="S">The pull request objectionary/lints#616 has been reviewed by @maxonfjvipon with 465 HoC and 5 comments.</details>
    <event_id t="I">50043965328</event_id>
    <event_type t="S">PullRequestReviewEvent</event_type>
    <files t="I">12</files>
    <hoc t="I">465</hoc>
    <is_human t="I">1</is_human>
    <issue t="I">616</issue>
    <repository t="I">889819508</repository>
    <review_comments t="I">0</review_comments>
    <what t="S">pull-was-reviewed</what>
    <when t="T">2025-05-22T20:14:37Z</when>
    <where t="S">github</where>
    <who t="I">37025995</who>
  </f>
  <f>
    <_id t="I">101</_id>
    <_time t="T">2025-06-11T04:34:23Z</_time>
    <_version t="S">0.9.10/0.39.2/</_version>
    <details t="S">The issue objectionary/lints#608 has been closed by @h1alexbel.</details>
    <event_id t="I">50029431247</event_id>
    <event_type t="S">IssuesEvent</event_type>
    <is_human t="I">1</is_human>
    <issue t="I">608</issue>
    <repository t="I">889819508</repository>
    <what t="S">issue-was-closed</what>
    <when t="T">2025-05-22T14:07:29Z</when>
    <where t="S">github</where>
    <who t="I">83453843</who>
  </f>
  <f>
    <_id t="I">102</_id>
    <_time t="T">2025-06-11T04:34:23Z</_time>
    <_version t="S">0.9.10/0.39.2/</_version>
    <branch t="S">608</branch>
    <comments t="I">4</comments>
    <comments_appreciated t="I">0</comments_appreciated>
    <comments_by_author t="I">3</comments_by_author>
    <comments_by_reviewers t="I">1</comments_by_reviewers>
    <comments_resolved t="I">0</comments_resolved>
    <comments_to_code t="I">0</comments_to_code>
    <details t="S">The pull request objectionary/lints#612 has been closed by @yegor256, with 191 HoC and 4 comments.</details>
    <event_id t="I">50028181408</event_id>
    <event_type t="S">PullRequestEvent</event_type>
    <failed_builds t="I">0</failed_builds>
    <hoc t="I">191</hoc>
    <is_human t="I">1</is_human>
    <issue t="I">612</issue>
    <repository t="I">889819508</repository>
    <succeeded_builds t="I">20</succeeded_builds>
    <what t="S">pull-was-merged</what>
    <when t="T">2025-05-22T13:43:12Z</when>
    <where t="S">github</where>
    <who t="I">526301</who>
  </f>
  <f>
    <_id t="I">103</_id>
    <_time t="T">2025-06-11T04:34:32Z</_time>
    <_version t="S">0.9.10/0.39.2/</_version>
    <comments t="I">4</comments>
    <commits t="I">3</commits>
    <details t="S">The pull request objectionary/lints#612 has been reviewed by @yegor256 with 191 HoC and 4 comments.</details>
    <event_id t="I">50028173246</event_id>
    <event_type t="S">PullRequestReviewEvent</event_type>
    <files t="I">3</files>
    <hoc t="I">191</hoc>
    <is_human t="I">1</is_human>
    <issue t="I">612</issue>
    <repository t="I">889819508</repository>
    <review_comments t="I">0</review_comments>
    <what t="S">pull-was-reviewed</what>
    <when t="T">2025-05-22T13:43:07Z</when>
    <where t="S">github</where>
    <who t="I">526301</who>
  </f>
  <f>
    <_id t="I">104</_id>
    <_time t="T">2025-06-11T04:34:33Z</_time>
    <_version t="S">0.9.10/0.39.2/</_version>
    <branch t="S">607</branch>
    <comments t="I">5</comments>
    <comments_appreciated t="I">1</comments_appreciated>
    <comments_by_author t="I">3</comments_by_author>
    <comments_by_reviewers t="I">3</comments_by_reviewers>
    <comments_resolved t="I">0</comments_resolved>
    <comments_to_code t="I">0</comments_to_code>
    <details t="S">The pull request objectionary/lints#614 has been closed by @yegor256, with 14 HoC and 5 comments.</details>
    <event_id t="I">50015173312</event_id>
    <event_type t="S">PullRequestEvent</event_type>
    <failed_builds t="I">0</failed_builds>
    <hoc t="I">14</hoc>
    <is_human t="I">1</is_human>
    <issue t="I">614</issue>
    <repository t="I">889819508</repository>
    <succeeded_builds t="I">20</succeeded_builds>
    <what t="S">pull-was-merged</what>
    <when t="T">2025-05-22T08:50:28Z</when>
    <where t="S">github</where>
    <who t="I">526301</who>
  </f>
  <f>
    <_id t="I">105</_id>
    <_time t="T">2025-06-11T04:34:42Z</_time>
    <_version t="S">0.9.10/0.39.2/</_version>
    <branch t="S">renovate/org.pitest-pitest-junit5-plugin-1.x</branch>
    <details t="S">The pull request objectionary/lints#611 has been opened by @renovate[bot].</details>
    <event_id t="I">49948045340</event_id>
    <event_type t="S">PullRequestEvent</event_type>
    <is_human t="I">0</is_human>
    <issue t="I">611</issue>
    <repository t="I">889819508</repository>
    <what t="S">pull-was-opened</what>
    <when t="T">2025-05-20T20:43:10Z</when>
    <where t="S">github</where>
    <who t="I">29139614</who>
  </f>
  <f>
    <_id t="I">106</_id>
    <_time t="T">2025-06-11T04:34:42Z</_time>
    <_version t="S">0.9.10/0.39.2/</_version>
    <details t="S">The issue objectionary/lints#595 has been closed by @h1alexbel.</details>
    <event_id t="I">49943238864</event_id>
    <event_type t="S">IssuesEvent</event_type>
    <is_human t="I">1</is_human>
    <issue t="I">595</issue>
    <repository t="I">889819508</repository>
    <what t="S">issue-was-closed</what>
    <when t="T">2025-05-20T18:22:15Z</when>
    <where t="S">github</where>
    <who t="I">83453843</who>
  </f>
  <f>
    <_id t="I">107</_id>
    <_time t="T">2025-06-11T04:34:42Z</_time>
    <_version t="S">0.9.10/0.39.2/</_version>
    <details t="S">The issue objectionary/lints#604 has been closed by @h1alexbel.</details>
    <event_id t="I">49943166351</event_id>
    <event_type t="S">IssuesEvent</event_type>
    <is_human t="I">1</is_human>
    <issue t="I">604</issue>
    <repository t="I">889819508</repository>
    <what t="S">issue-was-closed</what>
    <when t="T">2025-05-20T18:20:13Z</when>
    <where t="S">github</where>
    <who t="I">83453843</who>
  </f>
  <f>
    <_id t="I">108</_id>
    <_time t="T">2025-06-11T04:34:42Z</_time>
    <_version t="S">0.9.10/0.39.2/</_version>
    <details t="S">The issue objectionary/lints#562 has been closed by @h1alexbel.</details>
    <event_id t="I">49933799798</event_id>
    <event_type t="S">IssuesEvent</event_type>
    <is_human t="I">1</is_human>
    <issue t="I">562</issue>
    <repository t="I">889819508</repository>
    <what t="S">issue-was-closed</what>
    <when t="T">2025-05-20T14:34:15Z</when>
    <where t="S">github</where>
    <who t="I">83453843</who>
  </f>
  <f>
    <_id t="I">109</_id>
    <_time t="T">2025-06-11T04:34:42Z</_time>
    <_version t="S">0.9.10/0.39.2/</_version>
    <details t="S">The issue objectionary/lints#561 has been closed by @h1alexbel.</details>
    <event_id t="I">49933772707</event_id>
    <event_type t="S">IssuesEvent</event_type>
    <is_human t="I">1</is_human>
    <issue t="I">561</issue>
    <repository t="I">889819508</repository>
    <what t="S">issue-was-closed</what>
    <when t="T">2025-05-20T14:33:40Z</when>
    <where t="S">github</where>
    <who t="I">83453843</who>
  </f>
  <f>
    <_id t="I">110</_id>
    <_time t="T">2025-06-11T04:34:43Z</_time>
    <_version t="S">0.9.10/0.39.2/</_version>
    <details t="S">The issue objectionary/lints#610 has been opened by @h1alexbel.</details>
    <event_id t="I">49930252481</event_id>
    <event_type t="S">IssuesEvent</event_type>
    <is_human t="I">1</is_human>
    <issue t="I">610</issue>
    <repository t="I">889819508</repository>
    <what t="S">issue-was-opened</what>
    <when t="T">2025-05-20T13:24:55Z</when>
    <where t="S">github</where>
    <who t="I">83453843</who>
  </f>
  <f>
    <_id t="I">111</_id>
    <_time t="T">2025-06-11T04:34:43Z</_time>
    <_version t="S">0.9.10/0.39.2/</_version>
    <details t="S">The issue objectionary/lints#609 has been opened by @h1alexbel.</details>
    <event_id t="I">49929112750</event_id>
    <event_type t="S">IssuesEvent</event_type>
    <is_human t="I">1</is_human>
    <issue t="I">609</issue>
    <repository t="I">889819508</repository>
    <what t="S">issue-was-opened</what>
    <when t="T">2025-05-20T13:02:16Z</when>
    <where t="S">github</where>
    <who t="I">83453843</who>
  </f>
  <f>
    <_id t="I">112</_id>
    <_time t="T">2025-06-11T04:34:43Z</_time>
    <_version t="S">0.9.10/0.39.2/</_version>
    <details t="S">The issue objectionary/lints#608 has been opened by @h1alexbel.</details>
    <event_id t="I">49928488136</event_id>
    <event_type t="S">IssuesEvent</event_type>
    <is_human t="I">1</is_human>
    <issue t="I">608</issue>
    <repository t="I">889819508</repository>
    <what t="S">issue-was-opened</what>
    <when t="T">2025-05-20T12:49:23Z</when>
    <where t="S">github</where>
    <who t="I">83453843</who>
  </f>
  <f>
    <_id t="I">113</_id>
    <_time t="T">2025-06-11T04:35:01Z</_time>
    <_version t="S">0.9.10/0.39.2/</_version>
    <latest t="I">0</latest>
    <repository t="I">543969974</repository>
    <what t="S">labels-were-scanned</what>
    <where t="S">github</where>
  </f>
  <f>
    <_id t="I">114</_id>
    <_time t="T">2025-06-11T04:35:01Z</_time>
    <_version t="S">0.9.10/0.39.2/</_version>
    <latest t="I">0</latest>
    <repository t="I">519246071</repository>
    <what t="S">labels-were-scanned</what>
    <where t="S">github</where>
  </f>
  <f>
    <_id t="I">115</_id>
    <_time t="T">2025-06-11T04:35:01Z</_time>
    <_version t="S">0.9.10/0.39.2/</_version>
    <latest t="I">0</latest>
    <repository t="I">501259435</repository>
    <what t="S">labels-were-scanned</what>
    <where t="S">github</where>
  </f>
  <f>
    <_id t="I">116</_id>
    <_time t="T">2025-06-11T04:35:01Z</_time>
    <_version t="S">0.9.10/0.39.2/</_version>
    <latest t="I">0</latest>
    <repository t="I">510102039</repository>
    <what t="S">labels-were-scanned</what>
    <where t="S">github</where>
  </f>
  <f>
    <_id t="I">117</_id>
    <_time t="T">2025-06-11T04:35:01Z</_time>
    <_version t="S">0.9.10/0.39.2/</_version>
    <latest t="I">0</latest>
    <repository t="I">482612876</repository>
    <what t="S">labels-were-scanned</what>
    <where t="S">github</where>
  </f>
  <f>
    <_id t="I">118</_id>
    <_time t="T">2025-06-11T04:35:01Z</_time>
    <_version t="S">0.9.10/0.39.2/</_version>
    <latest t="I">0</latest>
    <repository t="I">13623548</repository>
    <what t="S">labels-were-scanned</what>
    <where t="S">github</where>
  </f>
  <f>
    <_id t="I">119</_id>
    <_time t="T">2025-06-11T04:35:01Z</_time>
    <_version t="S">0.9.10/0.39.2/</_version>
    <latest t="I">0</latest>
    <repository t="I">574534248</repository>
    <what t="S">labels-were-scanned</what>
    <where t="S">github</where>
  </f>
  <f>
    <_id t="I">120</_id>
    <_time t="T">2025-06-11T04:35:01Z</_time>
    <_version t="S">0.9.10/0.39.2/</_version>
    <latest t="I">0</latest>
    <repository t="I">501942888</repository>
    <what t="S">labels-were-scanned</what>
    <where t="S">github</where>
  </f>
  <f>
    <_id t="I">121</_id>
    <_time t="T">2025-06-11T04:35:01Z</_time>
    <_version t="S">0.9.10/0.39.2/</_version>
    <latest t="I">0</latest>
    <repository t="I">73056727</repository>
    <what t="S">labels-were-scanned</what>
    <where t="S">github</where>
  </f>
  <f>
    <_id t="I">122</_id>
    <_time t="T">2025-06-11T04:35:01Z</_time>
    <_version t="S">0.9.10/0.39.2/</_version>
    <latest t="I">0</latest>
    <repository t="I">490221501</repository>
    <what t="S">labels-were-scanned</what>
    <where t="S">github</where>
  </f>
  <f>
    <_id t="I">123</_id>
    <_time t="T">2025-06-11T04:35:01Z</_time>
    <_version t="S">0.9.10/0.39.2/</_version>
    <latest t="I">0</latest>
    <repository t="I">559427983</repository>
    <what t="S">labels-were-scanned</what>
    <where t="S">github</where>
  </f>
  <f>
    <_id t="I">124</_id>
    <_time t="T">2025-06-11T04:35:01Z</_time>
    <_version t="S">0.9.10/0.39.2/</_version>
    <latest t="I">0</latest>
    <repository t="I">574459304</repository>
    <what t="S">labels-were-scanned</what>
    <where t="S">github</where>
  </f>
  <f>
    <_id t="I">125</_id>
    <_time t="T">2025-06-11T04:35:01Z</_time>
    <_version t="S">0.9.10/0.39.2/</_version>
    <latest t="I">0</latest>
    <repository t="I">731516758</repository>
    <what t="S">labels-were-scanned</what>
    <where t="S">github</where>
  </f>
  <f>
    <_id t="I">126</_id>
    <_time t="T">2025-06-11T04:35:01Z</_time>
    <_version t="S">0.9.10/0.39.2/</_version>
    <details t="S">The '#bug' label was attached by @yegor256 to the issue objectionary/lints#608.</details>
    <issue t="I">608</issue>
    <label t="S">bug</label>
    <repository t="I">889819508</repository>
    <what t="S">label-was-attached</what>
    <when t="T">2025-05-20T14:32:09Z</when>
    <where t="S">github</where>
    <who t="I">526301</who>
  </f>
  <f>
    <_id t="I">128</_id>
    <_time t="T">2025-06-11T04:35:01Z</_time>
    <_version t="S">0.9.10/0.39.2/</_version>
    <latest t="I">0</latest>
    <repository t="I">447446664</repository>
    <what t="S">labels-were-scanned</what>
    <where t="S">github</where>
  </f>
  <f>
    <_id t="I">129</_id>
    <_time t="T">2025-06-11T04:35:01Z</_time>
    <_version t="S">0.9.10/0.39.2/</_version>
    <latest t="I">0</latest>
    <repository t="I">731438612</repository>
    <what t="S">labels-were-scanned</what>
    <where t="S">github</where>
  </f>
  <f>
    <_id t="I">130</_id>
    <_time t="T">2025-06-11T04:35:01Z</_time>
    <_version t="S">0.9.10/0.39.2/</_version>
    <latest t="I">0</latest>
    <repository t="I">499536612</repository>
    <what t="S">labels-were-scanned</what>
    <where t="S">github</where>
  </f>
  <f>
    <_id t="I">131</_id>
    <_time t="T">2025-06-11T04:35:01Z</_time>
    <_version t="S">0.9.10/0.39.2/</_version>
    <latest t="I">0</latest>
    <repository t="I">568705267</repository>
    <what t="S">labels-were-scanned</what>
    <where t="S">github</where>
  </f>
  <f>
    <_id t="I">132</_id>
    <_time t="T">2025-06-11T04:35:01Z</_time>
    <_version t="S">0.9.10/0.39.2/</_version>
    <latest t="I">0</latest>
    <repository t="I">784310467</repository>
    <what t="S">labels-were-scanned</what>
    <where t="S">github</where>
  </f>
  <f>
    <_id t="I">133</_id>
    <_time t="T">2025-06-11T04:35:01Z</_time>
    <_version t="S">0.9.10/0.39.2/</_version>
    <latest t="I">0</latest>
    <repository t="I">490157985</repository>
    <what t="S">labels-were-scanned</what>
    <where t="S">github</where>
  </f>
  <f>
    <_id t="I">134</_id>
    <_time t="T">2025-06-11T04:35:01Z</_time>
    <_version t="S">0.9.10/0.39.2/</_version>
    <latest t="I">0</latest>
    <repository t="I">570457023</repository>
    <what t="S">labels-were-scanned</what>
    <where t="S">github</where>
  </f>
  <f>
    <_id t="I">135</_id>
    <_time t="T">2025-06-11T04:35:02Z</_time>
    <_version t="S">0.9.10/0.39.2/</_version>
    <latest t="I">0</latest>
    <repository t="I">489321585</repository>
    <what t="S">labels-were-scanned</what>
    <where t="S">github</where>
  </f>
  <f>
    <_id t="I">136</_id>
    <_time t="T">2025-06-11T04:35:02Z</_time>
    <_version t="S">0.9.10/0.39.2/</_version>
    <latest t="I">0</latest>
    <repository t="I">519299365</repository>
    <what t="S">labels-were-scanned</what>
    <where t="S">github</where>
  </f>
  <f>
    <_id t="I">137</_id>
    <_time t="T">2025-06-11T04:35:02Z</_time>
    <_version t="S">0.9.10/0.39.2/</_version>
    <latest t="I">0</latest>
    <repository t="I">551486781</repository>
    <what t="S">labels-were-scanned</what>
    <where t="S">github</where>
  </f>
  <f>
    <_id t="I">138</_id>
    <_time t="T">2025-06-11T04:35:02Z</_time>
    <_version t="S">0.9.10/0.39.2/</_version>
    <latest t="I">0</latest>
    <repository t="I">565789755</repository>
    <what t="S">labels-were-scanned</what>
    <where t="S">github</where>
  </f>
  <f>
    <_id t="I">139</_id>
    <_time t="T">2025-06-11T04:35:02Z</_time>
    <_version t="S">0.9.10/0.39.2/</_version>
    <latest t="I">0</latest>
    <repository t="I">721146770</repository>
    <what t="S">labels-were-scanned</what>
    <where t="S">github</where>
  </f>
  <f>
    <_id t="I">140</_id>
    <_time t="T">2025-06-11T04:35:02Z</_time>
    <_version t="S">0.9.10/0.39.2/</_version>
    <latest t="I">0</latest>
    <repository t="I">483303722</repository>
    <what t="S">labels-were-scanned</what>
    <where t="S">github</where>
  </f>
  <f>
    <_id t="I">141</_id>
    <_time t="T">2025-06-11T04:35:02Z</_time>
    <_version t="S">0.9.10/0.39.2/</_version>
    <latest t="I">0</latest>
    <repository t="I">798766850</repository>
    <what t="S">labels-were-scanned</what>
    <where t="S">github</where>
  </f>
  <f>
    <_id t="I">142</_id>
    <_time t="T">2025-06-11T04:35:02Z</_time>
    <_version t="S">0.9.10/0.39.2/</_version>
    <latest t="I">0</latest>
    <repository t="I">403396472</repository>
    <what t="S">labels-were-scanned</what>
    <where t="S">github</where>
  </f>
  <f>
    <_id t="I">143</_id>
    <_time t="T">2025-06-11T04:35:02Z</_time>
    <_version t="S">0.9.10/0.39.2/</_version>
    <latest t="I">0</latest>
    <repository t="I">955159947</repository>
    <what t="S">labels-were-scanned</what>
    <where t="S">github</where>
  </f>
  <f>
    <_id t="I">144</_id>
    <_time t="T">2025-06-11T04:35:02Z</_time>
    <_version t="S">0.9.10/0.39.2/</_version>
    <latest t="I">0</latest>
    <repository t="I">493235807</repository>
    <what t="S">labels-were-scanned</what>
    <where t="S">github</where>
  </f>
  <f>
    <_id t="I">145</_id>
    <_time t="T">2025-06-11T04:35:02Z</_time>
    <_version t="S">0.9.10/0.39.2/</_version>
    <latest t="I">0</latest>
    <repository t="I">671896902</repository>
    <what t="S">labels-were-scanned</what>
    <where t="S">github</where>
  </f>
  <f>
    <_id t="I">146</_id>
    <_time t="T">2025-06-11T04:35:02Z</_time>
    <_version t="S">0.9.10/0.39.2/</_version>
    <latest t="I">0</latest>
    <repository t="I">970961472</repository>
    <what t="S">labels-were-scanned</what>
    <where t="S">github</where>
  </f>
  <f>
    <_id t="I">147</_id>
    <_time t="T">2025-06-11T04:35:02Z</_time>
    <_version t="S">0.9.10/0.39.2/</_version>
    <latest t="I">0</latest>
    <repository t="I">977982682</repository>
    <what t="S">labels-were-scanned</what>
    <where t="S">github</where>
  </f>
  <f>
    <_id t="I">148</_id>
    <_time t="T">2025-06-11T04:35:02Z</_time>
    <_version t="S">0.9.10/0.39.2/</_version>
    <latest t="I">0</latest>
    <repository t="I">531151981</repository>
    <what t="S">labels-were-scanned</what>
    <where t="S">github</where>
  </f>
  <f>
    <_id t="I">149</_id>
    <_time t="T">2025-06-11T04:35:02Z</_time>
    <_version t="S">0.9.10/0.39.2/</_version>
    <latest t="I">0</latest>
    <repository t="I">490258619</repository>
    <what t="S">labels-were-scanned</what>
    <where t="S">github</where>
  </f>
  <f>
    <_id t="I">150</_id>
    <_time t="T">2025-06-11T04:35:02Z</_time>
    <_version t="S">0.9.10/0.39.2/</_version>
    <latest t="I">0</latest>
    <repository t="I">840332960</repository>
    <what t="S">labels-were-scanned</what>
    <where t="S">github</where>
  </f>
  <f>
    <_id t="I">151</_id>
    <_time t="T">2025-06-11T04:35:02Z</_time>
    <_version t="S">0.9.10/0.39.2/</_version>
    <latest t="I">0</latest>
    <repository t="I">492899189</repository>
    <what t="S">labels-were-scanned</what>
    <where t="S">github</where>
  </f>
  <f>
    <_id t="I">152</_id>
    <_time t="T">2025-06-11T04:35:02Z</_time>
    <_version t="S">0.9.10/0.39.2/</_version>
    <latest t="I">0</latest>
    <repository t="I">733919301</repository>
    <what t="S">labels-were-scanned</what>
    <where t="S">github</where>
  </f>
  <f>
    <_id t="I">153</_id>
    <_time t="T">2025-06-11T04:35:02Z</_time>
    <_version t="S">0.9.10/0.39.2/</_version>
    <latest t="I">0</latest>
    <repository t="I">386420319</repository>
    <what t="S">labels-were-scanned</what>
    <where t="S">github</where>
  </f>
  <f>
    <_id t="I">154</_id>
    <_time t="T">2025-06-11T04:35:02Z</_time>
    <_version t="S">0.9.10/0.39.2/</_version>
    <latest t="I">0</latest>
    <repository t="I">558766137</repository>
    <what t="S">labels-were-scanned</what>
    <where t="S">github</where>
  </f>
  <f>
    <_id t="I">155</_id>
    <_time t="T">2025-06-11T04:35:02Z</_time>
    <_version t="S">0.9.10/0.39.2/</_version>
    <latest t="I">0</latest>
    <repository t="I">510082372</repository>
    <what t="S">labels-were-scanned</what>
    <where t="S">github</where>
  </f>
  <f>
    <_id t="I">156</_id>
    <_time t="T">2025-06-11T04:35:02Z</_time>
    <_version t="S">0.9.10/0.39.2/</_version>
    <latest t="I">0</latest>
    <repository t="I">396732517</repository>
    <what t="S">labels-were-scanned</what>
    <where t="S">github</where>
  </f>
  <f>
    <_id t="I">157</_id>
    <_time t="T">2025-06-11T04:35:02Z</_time>
    <_version t="S">0.9.10/0.39.2/</_version>
    <latest t="I">0</latest>
    <repository t="I">546194972</repository>
    <what t="S">labels-were-scanned</what>
    <where t="S">github</where>
  </f>
  <f>
    <_id t="I">158</_id>
    <_time t="T">2025-06-11T04:35:02Z</_time>
    <_version t="S">0.9.10/0.39.2/</_version>
    <latest t="I">0</latest>
    <repository t="I">624420387</repository>
    <what t="S">labels-were-scanned</what>
    <where t="S">github</where>
  </f>
  <f>
    <_id t="I">159</_id>
    <_time t="T">2025-06-11T04:35:02Z</_time>
    <_version t="S">0.9.10/0.39.2/</_version>
    <details t="S">The '#bug' label was attached by @yegor256 to the issue objectionary/lints#609.</details>
    <issue t="I">609</issue>
    <label t="S">bug</label>
    <repository t="I">889819508</repository>
    <what t="S">label-was-attached</what>
    <when t="T">2025-05-20T14:30:27Z</when>
    <where t="S">github</where>
    <who t="I">526301</who>
  </f>
  <f>
    <_id t="I">160</_id>
    <_time t="T">2025-06-11T04:35:03Z</_time>
    <_version t="S">0.9.10/0.39.2/</_version>
    <details t="S">The '#bug' label was attached by @yegor256 to the issue objectionary/lints#610.</details>
    <issue t="I">610</issue>
    <label t="S">bug</label>
    <repository t="I">889819508</repository>
    <what t="S">label-was-attached</what>
    <when t="T">2025-05-20T14:24:12Z</when>
    <where t="S">github</where>
    <who t="I">526301</who>
  </f>
  <f>
    <_id t="I">161</_id>
    <_time t="T">2025-06-11T04:35:04Z</_time>
    <_version t="S">0.9.10/0.39.2/</_version>
    <details t="S">The '#bug' label was attached by @yegor256 to the issue objectionary/lints#624.</details>
    <issue t="I">624</issue>
    <label t="S">bug</label>
    <repository t="I">889819508</repository>
    <what t="S">label-was-attached</what>
    <when t="T">2025-06-03T06:51:22Z</when>
    <where t="S">github</where>
    <who t="I">526301</who>
  </f>
  <f>
    <_id t="I">162</_id>
    <_time t="T">2025-06-11T04:35:04Z</_time>
    <_version t="S">0.9.10/0.39.2/</_version>
    <details t="S">The '#bug' label was attached by @0pdd to the issue objectionary/lints#627.</details>
    <issue t="I">627</issue>
    <label t="S">bug</label>
    <repository t="I">889819508</repository>
    <what t="S">label-was-attached</what>
    <when t="T">2025-06-06T08:43:10Z</when>
    <where t="S">github</where>
    <who t="I">24456188</who>
  </f>
  <f>
    <_id t="I">163</_id>
    <_time t="T">2025-06-11T04:35:05Z</_time>
    <_version t="S">0.9.10/0.39.2/</_version>
    <details t="S">The '#bug' label was attached by @h1alexbel to the issue objectionary/lints#630.</details>
    <issue t="I">630</issue>
    <label t="S">bug</label>
    <repository t="I">889819508</repository>
    <what t="S">label-was-attached</what>
    <when t="T">2025-06-06T13:00:27Z</when>
    <where t="S">github</where>
    <who t="I">83453843</who>
  </f>
  <f>
    <_id t="I">164</_id>
    <_time t="T">2025-06-11T04:35:05Z</_time>
    <_version t="S">0.9.10/0.39.2/</_version>
    <details t="S">The '#bug' label was attached by @yegor256 to the issue objectionary/lints#632.</details>
    <issue t="I">632</issue>
    <label t="S">bug</label>
    <repository t="I">889819508</repository>
    <what t="S">label-was-attached</what>
    <when t="T">2025-06-08T09:57:22Z</when>
    <where t="S">github</where>
    <who t="I">526301</who>
  </f>
  <f>
    <_id t="I">165</_id>
    <_time t="T">2025-06-11T04:35:05Z</_time>
    <_version t="S">0.9.10/0.39.2/</_version>
    <details t="S">The '#bug' label was attached by @yegor256 to the issue objectionary/lints#634.</details>
    <issue t="I">634</issue>
    <label t="S">bug</label>
    <repository t="I">889819508</repository>
    <what t="S">label-was-attached</what>
    <when t="T">2025-06-08T16:25:42Z</when>
    <where t="S">github</where>
    <who t="I">526301</who>
  </f>
  <f>
    <_id t="I">166</_id>
    <_time t="T">2025-06-11T04:35:05Z</_time>
    <_version t="S">0.9.10/0.39.2/</_version>
    <details t="S">The '#bug' label was attached by @yegor256 to the issue objectionary/lints#635.</details>
    <issue t="I">635</issue>
    <label t="S">bug</label>
    <repository t="I">889819508</repository>
    <what t="S">label-was-attached</what>
    <when t="T">2025-06-08T16:31:00Z</when>
    <where t="S">github</where>
    <who t="I">526301</who>
  </f>
  <f>
    <_id t="I">167</_id>
    <_time t="T">2025-06-11T04:35:05Z</_time>
    <_version t="S">0.9.10/0.39.2/</_version>
    <details t="S">The '#bug' label was attached by @yegor256 to the issue objectionary/lints#636.</details>
    <issue t="I">636</issue>
    <label t="S">bug</label>
    <repository t="I">889819508</repository>
    <what t="S">label-was-attached</what>
    <when t="T">2025-06-08T17:05:02Z</when>
    <where t="S">github</where>
    <who t="I">526301</who>
  </f>
  <f>
    <_id t="I">168</_id>
    <_time t="T">2025-06-11T04:35:06Z</_time>
    <_version t="S">0.9.10/0.39.2/</_version>
    <details t="S">The '#bug' label was attached by @yegor256 to the issue objectionary/lints#637.</details>
    <issue t="I">637</issue>
    <label t="S">bug</label>
    <repository t="I">889819508</repository>
    <what t="S">label-was-attached</what>
    <when t="T">2025-06-08T17:13:42Z</when>
    <where t="S">github</where>
    <who t="I">526301</who>
  </f>
  <f>
    <_id t="I">169</_id>
    <_time t="T">2025-06-11T04:35:06Z</_time>
    <_version t="S">0.9.10/0.39.2/</_version>
    <latest t="I">0</latest>
    <repository t="I">889819508</repository>
    <what t="S">labels-were-scanned</what>
    <where t="S">github</where>
  </f>
  <f>
    <_id t="I">170</_id>
    <_time t="T">2025-06-11T04:36:17Z</_time>
    <_version t="S">0.9.10/0.39.2/</_version>
    <average_triage_time t="F">8596.818181818182</average_triage_time>
    <since t="T">2025-05-14T04:35:06Z</since>
    <what t="S">quality-of-service</what>
    <when t="T">2025-06-11T04:35:06Z</when>
  </f>
</fb>
